Workbook

Sheet Hypothèses
B2: Fait par Marcel CHANARD | F2: Hypothèses & scénarios
B4: Scénario actif : | C4: Optimiste
B6: Hypothèse | C6: Base | D6: Optimiste | E6: Pessimiste | H6: Hypothèse active | I6: Valeur
B7: Croissance volumes | C7: 0.08 | D7: 0.12 | E7: 0.04 | H7: Croissance volumes | I7: =INDEX($C$7:$E$13,MATCH(H7,$B$7:$B$13,0),MATCH($C$4,$C$6:$E$6,0)) -> 0.12
B8: Croissance prix | C8: 0.03 | D8: 0.04 | E8: 0.01 | H8: Croissance prix | I8: =INDEX($C$7:$E$13,MATCH(H8,$B$7:$B$13,0),MATCH($C$4,$C$6:$E$6,0)) -> 0.04
B9: Coût variable (% CA) | C9: 0.42 | D9: 0.39 | E9: 0.46 | H9: Coût variable (% CA) | I9: =INDEX($C$7:$E$13,MATCH(H9,$B$7:$B$13,0),MATCH($C$4,$C$6:$E$6,0)) -> 0.39
B10: Inflation charges fixes | C10: 0.02 | D10: 0.02 | E10: 0.03 | H10: Inflation charges fixes | I10: =INDEX($C$7:$E$13,MATCH(H10,$B$7:$B$13,0),MATCH($C$4,$C$6:$E$6,0)) -> 0.02
B11: CAPEX (% CA) | C11: 0.06 | D11: 0.05 | E11: 0.07 | H11: Capex (% CA) | I11: =INDEX($C$7:$E$13,MATCH(H11,$B$7:$B$13,0),MATCH($C$4,$C$6:$E$6,0)) -> 0.05
B12: BFR (% CA) | C12: 0.08 | D12: 0.07 | E12: 0.09 | H12: BFR (% CA) | I12: =INDEX($C$7:$E$13,MATCH(H12,$B$7:$B$13,0),MATCH($C$4,$C$6:$E$6,0)) -> 0.07
B13: Taux IS | C13: 0.25 | D13: 0.25 | E13: 0.25 | H13: Taux IS | I13: =INDEX($C$7:$E$13,MATCH(H13,$B$7:$B$13,0),MATCH($C$4,$C$6:$E$6,0)) -> 0.25
B16: Données de départ (2025)
B17: Produit | C17: Volume 2025 | D17: Prix unitaire 2025
B18: Abonnement | C18: 1200 | D18: 29
B19: Formation | C19: 180 | D19: 890
B20: Conseil | C20: 75 | D20: 3200
B22: Charges fixes 2025 | C22: 95000

Sheet Ventes
B2: Fait par Marcel CHANARD | F2: Projections et ventes
C6: 2025A | D6: 2026E | E6: 2027E | F6: 2028E | G6: 2029E | H6: 2030E
B7: Abonnement
B8: Volume | C8: =Hypothèses!C18 -> 1200 | D8: =C8*(1+Hypothèses!$I$7) -> 1344 | E8: =D8*(1+Hypothèses!$I$7) -> 1505.28 | F8: =E8*(1+Hypothèses!$I$7) -> 1685.9136 | G8: =F8*(1+Hypothèses!$I$7) -> 1888.2232 | H8: =G8*(1+Hypothèses!$I$7) -> 2114.81
B9: Prix unitaire | C9: =Hypothèses!D18 -> 29 | D9: =C9*(1+Hypothèses!$I$8) -> 30.16 | E9: =D9*(1+Hypothèses!$I$8) -> 31.3664 | F9: =E9*(1+Hypothèses!$I$8) -> 32.621056 | G9: =F9*(1+Hypothèses!$I$8) -> 33.925898 | H9: =G9*(1+Hypothèses!$I$8) -> 35.282934
B10: CA | C10: =C9*C8 -> 34800 | D10: =D9*D8 -> 40535.04 | E10: =E9*E8 -> 47215.215 | F10: =F9*F8 -> 54996.282 | G10: =G9*G8 -> 64059.669 | H10: =H9*H8 -> 74616.703 | M10: =B7 -> Abonnement | N10: =H10 -> 74616.703
B11: Formation | M11: =B11 -> Formation | N11: =H14 -> 343494.13
B12: Volume | C12: =Hypothèses!C19 -> 180 | D12: =C12*(1+Hypothèses!$I$7) -> 201.6 | E12: =D12*(1+Hypothèses!$I$7) -> 225.792 | F12: =E12*(1+Hypothèses!$I$7) -> 252.88704 | G12: =F12*(1+Hypothèses!$I$7) -> 283.23348 | H12: =G12*(1+Hypothèses!$I$7) -> 317.2215 | M12: =B15 -> Conseil | N12: =H18 -> 514597.95
B13: Prix unitaire | C13: =Hypothèses!D19 -> 890 | D13: =C13*(1+Hypothèses!$I$8) -> 925.6 | E13: =D13*(1+Hypothèses!$I$8) -> 962.624 | F13: =E13*(1+Hypothèses!$I$8) -> 1001.129 | G13: =F13*(1+Hypothèses!$I$8) -> 1041.1741 | H13: =G13*(1+Hypothèses!$I$8) -> 1082.8211
B14: CA | C14: =C13*C12 -> 160200 | D14: =D13*D12 -> 186600.96 | E14: =E13*E12 -> 217352.8 | F14: =F13*F12 -> 253172.54 | G14: =G13*G12 -> 294895.37 | H14: =H13*H12 -> 343494.13
B15: Conseil
B16: Volume | C16: =Hypothèses!C20 -> 75 | D16: =C16*(1+Hypothèses!$I$7) -> 84 | E16: =D16*(1+Hypothèses!$I$7) -> 94.08 | F16: =E16*(1+Hypothèses!$I$7) -> 105.3696 | G16: =F16*(1+Hypothèses!$I$7) -> 118.01395 | H16: =G16*(1+Hypothèses!$I$7) -> 132.17563
B17: Prix unitaire | C17: =Hypothèses!D20 -> 3200 | D17: =C17*(1+Hypothèses!$I$8) -> 3328 | E17: =D17*(1+Hypothèses!$I$8) -> 3461.12 | F17: =E17*(1+Hypothèses!$I$8) -> 3599.5648 | G17: =F17*(1+Hypothèses!$I$8) -> 3743.5474 | H17: =G17*(1+Hypothèses!$I$8) -> 3893.2893
B18: CA | C18: =C17*C16 -> 240000 | D18: =D17*D16 -> 279552 | E18: =E17*E16 -> 325622.17 | F18: =F17*F16 -> 379284.7 | G18: =G17*G16 -> 441790.82 | H18: =H17*H16 -> 514597.95
B20: Total CA | C20: =C10+C14+C18 -> 435000 | D20: =D10+D14+D18 -> 506688 | E20: =E10+E14+E18 -> 590190.18 | F20: =F10+F14+F18 -> 687453.52 | G20: =G10+G14+G18 -> 800745.87 | H20: =H10+H14+H18 -> 932708.78

Sheet Charges et FCF
B2: Fait par Marcel CHANARD | F2: Charges, résultat & FCF
D5: 2025A | E5: 2026E | F5: 2027E | G5: 2028E | H5: 2029E | I5: 2030E
B6: Total CA | D6: =Ventes!C20 -> 435000 | E6: =Ventes!D20 -> 506688 | F6: =Ventes!E20 -> 590190.18 | G6: =Ventes!F20 -> 687453.52 | H6: =Ventes!G20 -> 800745.87 | I6: =Ventes!H20 -> 932708.78
B7: Couts variables | C7: - | D7: =D6*(Hypothèses!$I$9) -> 169650 | E7: =E6*(Hypothèses!$I$9) -> 197608.32 | F7: =F6*(Hypothèses!$I$9) -> 230174.17 | G7: =G6*(Hypothèses!$I$9) -> 268106.87 | H7: =H6*(Hypothèses!$I$9) -> 312290.89 | I7: =I6*(Hypothèses!$I$9) -> 363756.43
B8: Marge brute | D8: =D6-D7 -> 265350 | E8: =E6-E7 -> 309079.68 | F8: =F6-F7 -> 360016.01 | G8: =G6-G7 -> 419346.65 | H8: =H6-H7 -> 488454.98 | I8: =I6-I7 -> 568952.36
B9: Charges fixes | C9: - | D9: =Hypothèses!C22 -> 95000 | E9: =D9+(D9*Hypothèses!$I$10) -> 96900 | F9: =E9+(E9*Hypothèses!$I$10) -> 98838 | G9: =F9+(F9*Hypothèses!$I$10) -> 100814.76 | H9: =G9+(G9*Hypothèses!$I$10) -> 102831.06 | I9: =H9+(H9*Hypothèses!$I$10) -> 104887.68
B10: EBITDA | D10: =D8-D9 -> 170350 | E10: =E8-E9 -> 212179.68 | F10: =F8-F9 -> 261178.01 | G10: =G8-G9 -> 318531.89 | H10: =H8-H9 -> 385623.92 | I10: =I8-I9 -> 464064.68
B11: Dotations aux amortissements | C11: - | D11: =D15/5 -> 4350 | E11: =E15/5 -> 5066.88 | F11: =F15/5 -> 5901.9018 | G11: =G15/5 -> 6874.5352 | H11: =H15/5 -> 8007.4587 | I11: =I15/5 -> 9327.0878
B12: EBIT | D12: =D10-D11 -> 166000 | E12: =E10-E11 -> 207112.8 | F12: =F10-F11 -> 255276.11 | G12: =G10-G11 -> 311657.35 | H12: =H10-H11 -> 377616.46 | I12: =I10-I11 -> 454737.59
B13: Impot sur EBIT | C13: - | D13: =D12*Hypothèses!$I$13 -> 41500 | E13: =E12*Hypothèses!$I$13 -> 51778.2 | F13: =F12*Hypothèses!$I$13 -> 63819.027 | G13: =G12*Hypothèses!$I$13 -> 77914.339 | H13: =H12*Hypothèses!$I$13 -> 94404.116 | I13: =I12*Hypothèses!$I$13 -> 113684.4
B14: NOPAT | D14: =D12-D13 -> 124500 | E14: =E12-E13 -> 155334.6 | F14: =F12-F13 -> 191457.08 | G14: =G12-G13 -> 233743.02 | H14: =H12-H13 -> 283212.35 | I14: =I12-I13 -> 341053.2
B15: Capex | C15: - | D15: =D6*Hypothèses!$I$11 -> 21750 | E15: =E6*Hypothèses!$I$11 -> 25334.4 | F15: =F6*Hypothèses!$I$11 -> 29509.509 | G15: =G6*Hypothèses!$I$11 -> 34372.676 | H15: =H6*Hypothèses!$I$11 -> 40037.293 | I15: =I6*Hypothèses!$I$11 -> 46635.439
B16: BFR | D16: =D6*Hypothèses!$I$12 -> 30450 | E16: =E6*Hypothèses!$I$12 -> 35468.16 | F16: =F6*Hypothèses!$I$12 -> 41313.313 | G16: =G6*Hypothèses!$I$12 -> 48121.747 | H16: =H6*Hypothèses!$I$12 -> 56052.211 | I16: =I6*Hypothèses!$I$12 -> 65289.615
B17: Variation du BFR | C17: - | D17: 0 | E17: =E16-D16 -> 5018.16 | F17: =F16-E16 -> 5845.1528 | G17: =G16-F16 -> 6808.4339 | H17: =H16-G16 -> 7930.4639 | I17: =I16-H16 -> 9237.4043
B18: FCF | C18: = | D18: =D14+D11-D15-D17 -> 107100 | E18: =E14+E11-E15-E17 -> 130048.92 | F18: =F14+F11-F15-F17 -> 162004.32 | G18: =G14+G11-G15-G17 -> 199436.44 | H18: =H14+H11-H15-H17 -> 243252.05 | I18: =I14+I11-I15-I17 -> 294507.44
B20: FCF = NOPAT + amoritssements - CAPEX - variation BFR

Sheet Analyse
B2: Fait par Marcel CHANARD | F2: Analyse financière
C6: 2025A | D6: 2026E | E6: 2027E | F6: 2028E | G6: 2029E | H6: 2030E | J6: Indicateurs cles
B7: Croissance du CA | D7: =('Charges et FCF'!E6/'Charges et FCF'!D6)-1 -> 0.1648 | E7: =('Charges et FCF'!F6/'Charges et FCF'!E6)-1 -> 0.1648 | F7: =('Charges et FCF'!G6/'Charges et FCF'!F6)-1 -> 0.1648 | G7: =('Charges et FCF'!H6/'Charges et FCF'!G6)-1 -> 0.1648 | H7: =('Charges et FCF'!I6/'Charges et FCF'!H6)-1 -> 0.1648 | J7: CA 2030 | K7: =Ventes!H20 -> 932708.78
B8: Marge brute % | C8: ='Charges et FCF'!D8/'Charges et FCF'!D6 -> 0.61 | D8: ='Charges et FCF'!E8/'Charges et FCF'!E6 -> 0.61 | E8: ='Charges et FCF'!F8/'Charges et FCF'!F6 -> 0.61 | F8: ='Charges et FCF'!G8/'Charges et FCF'!G6 -> 0.61 | G8: ='Charges et FCF'!H8/'Charges et FCF'!H6 -> 0.61 | H8: ='Charges et FCF'!I8/'Charges et FCF'!I6 -> 0.61 | J8: EBITDA 2030 | K8: ='Charges et FCF'!I10 -> 464064.68
B9: Marge EBITDA % | C9: ='Charges et FCF'!D10/'Charges et FCF'!D6 -> 0.3916092 | D9: ='Charges et FCF'!E10/'Charges et FCF'!E6 -> 0.41875805 | E9: ='Charges et FCF'!F10/'Charges et FCF'!F6 -> 0.44253195 | F9: ='Charges et FCF'!G10/'Charges et FCF'!G6 -> 0.46335044 | G9: ='Charges et FCF'!H10/'Charges et FCF'!H6 -> 0.48158091 | H9: ='Charges et FCF'!I10/'Charges et FCF'!I6 -> 0.4975451 | J9: Marge EBITDA 2030 | K9: =H9 -> 0.4975451
B10: Marge EBIT % | C10: ='Charges et FCF'!D12/'Charges et FCF'!D6 -> 0.3816092 | D10: ='Charges et FCF'!E12/'Charges et FCF'!E6 -> 0.40875805 | E10: ='Charges et FCF'!F12/'Charges et FCF'!F6 -> 0.43253195 | F10: ='Charges et FCF'!G12/'Charges et FCF'!G6 -> 0.45335044 | G10: ='Charges et FCF'!H12/'Charges et FCF'!H6 -> 0.47158091 | H10: ='Charges et FCF'!I12/'Charges et FCF'!I6 -> 0.4875451 | J10: FCF Cumule 2025-2030 | K10: =SUM('Charges et FCF'!D18:I18) -> 1136349.2
B11: Conversion FCF / EBITDA | C11: ='Charges et FCF'!D18/'Charges et FCF'!D10 -> 0.62870561 | D11: ='Charges et FCF'!E18/'Charges et FCF'!E10 -> 0.61291882 | E11: ='Charges et FCF'!F18/'Charges et FCF'!F10 -> 0.62028316 | F11: ='Charges et FCF'!G18/'Charges et FCF'!G10 -> 0.62611138 | G11: ='Charges et FCF'!H18/'Charges et FCF'!H10 -> 0.63080124 | H11: ='Charges et FCF'!I18/'Charges et FCF'!I10 -> 0.63462584 | J11: CAGR du CA 2025-2030 | K11: =('Charges et FCF'!I6/'Charges et FCF'!D6)^(1/5)-1 -> 0.1648
J12: CAGR EBITDA 2025-2030 | K12: =('Charges et FCF'!I10/'Charges et FCF'!D10)^(1/5)-1 -> 0.22193267
J13: Marge EBITDA moyenne | K13: =AVERAGE('Charges et FCF'!E10:I10) -> 328315.64
J14: Point mort 2026 | K14: ='Charges et FCF'!I9/Analyse!H8 -> 171947.01
B15: Comparaison rapide des scenarios (2030)
B16: Scenario | C16: CA 2030 | D16: EBITDA 2030 | E16: Marge EBITDA | F16: Commentaires
B17: Base | C17: =SUM( Hypothèses!$C$18*(1+Hypothèses!C7)^5*Hypothèses!$D$18*(1+Hypothèses!C8)^5, Hypothèses!$C$19*(1+Hypothèses!C7)^5*Hypothèses!$D$19*(1+Hypothèses!C8)^5, Hypothèses!$C$20*(1+Hypothèses!C7)^5*Hypothèses!$D$20*(1+Hypothèses!C8)^5 ) -> 740958.97 | D17: 324869 | E17: 0.4384 | F17: Croissance stable
B18: Optimiste | C18: =((Hypothèses!$C$18*(1+Hypothèses!D7)^5))*(Hypothèses!$D$18*(1+Hypothèses!D$8)^5)+((Hypothèses!$C$19*(1+Hypothèses!D7)^5))*(Hypothèses!$D$19*(1+Hypothèses!D$8)^5)+((Hypothèses!$C$20*(1+Hypothèses!D7)^5))*(Hypothèses!$D$20*(1+Hypothèses!$D$8)^5) -> 932708.78 | D18: 464064 | E18: 0.4975 | F18: Forte croissance
B19: Pessimiste | C19: =((Hypothèses!$C$18*(1+Hypothèses!E7)^5))*(Hypothèses!$D$18*(1+Hypothèses!E8)^5)+((Hypothèses!$C$19*(1+Hypothèses!E7)^5))*(Hypothèses!$D$19*(1+Hypothèses!E8)^5)+((Hypothèses!$C$20*(1+Hypothèses!E7)^5))*(Hypothèses!$D$20*(1+Hypothèses!E8)^5) -> 556240.78 | D19: 190238 | E19: 0.342 | F19: Pression sur marges

Sheet Tableau de bord
B2: Fait par Marcel CHANARD | F2: Tableau de bord — Modèle financier
J3: Scénario actif | W3: CA 2030 | Y3: EBITDA 2030 | AA3: Marge EBITDA 2030 | AC3: FCF Cumule
J4: =Hypothèses!C4 -> Optimiste | W4: =Ventes!H20 -> 932708.78 | Y4: ='Charges et FCF'!I10 -> 464064.68 | AA4: =Analyse!H9 -> 0.4975451 | AC4: =SUM(SUM('Charges et FCF'!D18:I18)) -> 1136349.2
B6: CA 2030 | F6: EBITDA 2030 | J6: =IF(Hypothèses!C4="Optimiste","Le scénario optimiste combine volume et prix plus dynamiques, ce qui tire fortement le CA et l'EBITDA.","Le scénario actif influence directement la trajectoire de CA, de marge et de cash-flow.") -> Le scénario optimiste combine volume et prix plus dynamiques, ce qui tire fortement le CA et l'EBITDA.
B7: ='Charges et FCF'!I6 -> 932708.78 | F7: =Analyse!K8 -> 464064.68
B10: CAGR du CA | F10: Point mort 2026 | J10: =_xlfn.CONCAT("Volumes : ",TEXT(Hypothèses!I7,"0,0%")," | Prix : ",TEXT(Hypothèses!I8,"0,0%")," | Coût variable : ",TEXT(Hypothèses!I9,"0,0%")," | CAPEX : ",TEXT(Hypothèses!I11,"0,0%")," | BFR : ",TEXT(Hypothèses!I12,"0,0%")) -> Volumes : 12,0% | Prix : 4,0% | Coût variable : 39,0% | CAPEX : 5,0% | BFR : 7,0%
B11: =Analyse!K11 -> 0.1648 | F11: =Analyse!K14 -> 171947.01
B16: Trajectoire opérationnelle | H16: Rentabilité & croissance
B33: Génération de cash | H33: Mix de valeur 2030
B49: Profil des scénarios
H52: Matrice scénarios 2030
H53: Scénario | I53: CA 2030 | J53: EBITDA 2030 | K53: Marge EBITDA | L53: Lecture
H54: =Hypothèses!C6 -> Base | I54: =Analyse!C17 -> 740958.97 | J54: =Analyse!D17 -> 324869 | K54: =Analyse!E17 -> 0.4384 | L54: =Analyse!F17 -> Croissance stable
H55: =Hypothèses!D6 -> Optimiste | I55: =Analyse!C18 -> 932708.78 | J55: =Analyse!D18 -> 464064 | K55: =Analyse!E18 -> 0.4975 | L55: =Analyse!F18 -> Forte croissance
H56: =Hypothèses!E6 -> Pessimiste | I56: =Analyse!C19 -> 556240.78 | J56: =Analyse!D19 -> 190238 | K56: =Analyse!E19 -> 0.342 | L56: =Analyse!F19 -> Pression sur marges
